Design_phase/5_Debouncing_Circuit/Counter.v
//////////////////////////////////////////////////////////////////////////////// 
// Author: Hatem Essam 
// Course: NTI HireReady Digital IC 
// 
// Description: clock divider
// Referance : 
//
//////////////////////////////////////////////////////////////////////////////// 

module counter  (
    clk , rst_n, m_tick
);


input wire clk, rst_n ;
output reg m_tick;

localparam CLK_FREQ = 100_000_000; //clk input in hz 100 mhz is 10 ns
localparam CLK_DIVIDER = 10_000_000; // 10 mhz is 100 ns
// tick every 100 ns 
localparam COUNTER_MAX = (CLK_FREQ / CLK_DIVIDER);
reg [$clog2(COUNTER_MAX) -1 :0] counter ;

always @(posedge clk or negedge rst_n) begin
    
    if ( ~rst_n ) begin
        m_tick <= 0;
        counter <= 0;
    end 
    else begin
        if (counter == (COUNTER_MAX)) begin
            counter <= 0;
            m_tick <= 1;
        end else begin
            counter <= counter +1;
            m_tick <= 0;
        end
    end

end






    
endmodule

Debouncing_Circuit.v
/*


*/

module Debouncing_Circuit(
    sw_signal, db , clk,rst_n
);
    
    // -------------------------------------------------------------
    // STATES
    // -------------------------------------------------------------
        localparam ZERO    = 4'b0000;
        localparam WAIT1_1 = 4'b0001;
        localparam WAIT1_2 = 4'b0011;
        localparam WAIT1_3 = 4'b0010;

        localparam ONE     = 4'b1000;
        localparam WAIT0_1 = 4'b1001;
        localparam WAIT0_2 = 4'b1011;
        localparam WAIT0_3 = 4'b1010;


input wire sw_signal;
input wire clk,rst_n;
output reg db;

reg [3:0] current_state, next_state;
wire m_tick;


    // -------------------------------------------------------------
    // counter inst
    // -------------------------------------------------------------
counter  counter (
    .clk(clk) , 
    .rst_n(rst_n), 
    .m_tick(m_tick)
);

    // -------------------------------------------------------------
    // 1. Combinational Logic: Next State Logic
    // -------------------------------------------------------------
    always @(*) begin
        case (current_state)
        ///////////////////////////////
        //zERO to ONE
        //////////////////////////////
            ZERO: begin
                if ( ~ sw_signal) begin
                    next_state = ZERO;
                end 
                else begin
                    next_state = WAIT1_1;
                end
            end
            WAIT1_1: begin
                if ( ~ sw_signal) begin
                    next_state = ZERO;
                end 
                else if (sw_signal && (~m_tick)) begin
                    next_state = WAIT1_1;
                end else if (sw_signal && m_tick) begin
                    next_state = WAIT1_2;
                end else begin
                    next_state = WAIT1_1; // just for closing the branch
                end
            end
            WAIT1_2: begin
                if ( ~ sw_signal) begin
                    next_state = ZERO;
                end 
                else if (sw_signal && (~m_tick)) begin
                    next_state = WAIT1_2;
                end else if (sw_signal && m_tick) begin
                    next_state = WAIT1_3;
                end else begin
                    next_state = WAIT1_2; // just for closing the branch
                end
            end
            WAIT1_3: begin
                if ( ~ sw_signal) begin
                    next_state = ZERO;
                end 
                else if (sw_signal && (~m_tick)) begin
                    next_state = WAIT1_3;
                end else if (sw_signal && m_tick) begin
                    next_state = ONE;
                end else begin
                    next_state = WAIT1_3; // just for closing the branch
                end
            end

        ///////////////////////////////
        //ONE to ZERO
        //////////////////////////////
            ONE: begin
                if ( sw_signal) begin
                    next_state = ONE;
                end 
                else begin
                    next_state = WAIT0_1;
                end
            end
            WAIT0_1: begin
                if ( sw_signal) begin
                    next_state = ONE;
                end 
                else if ( (~sw_signal) && (~m_tick)) begin
                    next_state = WAIT0_1;
                end else if ( (~sw_signal) && m_tick) begin
                    next_state = WAIT0_2;
                end else begin
                    next_state = WAIT0_1; // just for closing the branch
                end
            end
            WAIT0_2: begin
                if ( sw_signal) begin
                    next_state = ONE;
                end 
                else if ((~sw_signal) && (~m_tick)) begin
                    next_state = WAIT0_2;
                end else if ((~sw_signal) && m_tick) begin
                    next_state = WAIT0_3;
                end else begin
                    next_state = WAIT0_2; // just for closing the branch
                end
            end
            WAIT0_3: begin
                if ( sw_signal) begin
                    next_state = ONE;
                end 
                else if ((~sw_signal) && (~m_tick)) begin
                    next_state = WAIT0_3;
                end else if ((~sw_signal) && m_tick) begin
                    next_state = ZERO;
                end else begin
                    next_state = WAIT0_3; // just for closing the branch
                end
            end

            //////////////////////////////////////////////////////////
            default: begin // for unvalid opcodes
                next_state = ZERO;
            end
        endcase
    
    end



    // -------------------------------------------------------------
    // 2. Sequential Logic: State Register
    // -------------------------------------------------------------
    always @(posedge clk or negedge rst_n) begin
            if (~ rst_n) begin
                current_state <= ZERO;
            end else begin
                current_state <= next_state;
            end
    end
    

    // -------------------------------------------------------------
    // 3. Output block
    // -------------------------------------------------------------

    always @(*) begin


    // The Moore FSM Output Logic depend on  current state

        if ((current_state == ZERO) || (current_state == WAIT1_1) || (current_state == WAIT1_2) || (current_state == WAIT1_3))
            db = 1'b0;
        else if ((current_state == ONE) || (current_state == WAIT0_1) || (current_state == WAIT0_2) || (current_state == WAIT0_3))
            db = 1'b1;
        else  db = 1'b0;  // just for closing the branch

    end




endmodule

Design_phase/5_Debouncing_Circuit/tb_Debouncing_Circuit.v
//////////////////////////////////////////////////////////////////////////////// 
// Author: Hatem Essam 
// Course: NTI HireReady Digital IC 
// 
// Description: Simple testbench for depouncing circuit for observing waveform
// Referance : 
//
//////////////////////////////////////////////////////////////////////////////// 

module tb_Debouncing_Circuit ();

reg rst_n, clk;
reg sw_signal;
wire db;


Debouncing_Circuit Debouncing_Circuit_UUT (
    .sw_signal(sw_signal), 
    .db(db) , 
    .clk(clk),
    .rst_n(rst_n)
);


//initial begin

/* 
    initial begin
    // 1. Specify the output waveform file name
    $dumpfile("waveform.vcd");
    
    // 2. Dump all signals from the testbench downward recursively
    $dumpvars(0, tb_top); 
    
    // Alternatively, to dump ONLY the DUT and its immediate contents:
    // $dumpvars(1, dut); 
    
    // Alternatively, to dump only specific signals:
    // $dumpvars(0, clk, reset);
    end */



    //$dumpfile ("Debouncing_Circuit.vcd");
    //$dumpvars (level, list_of_modules_or_variables);
    //level is 
    //$dumpvars (0, tb_Debouncing_Circuit);

//end 



    initial begin
        clk =0;
        forever begin 
            #5 clk = ~clk;
        end 
    end 




initial begin


    sw_signal = 0;
    rst_n = 0;
    @(negedge clk);  
    rst_n = 1;
    #1;


    repeat (20) begin
    sw_signal = 1;
    #1;
    sw_signal = 0;
    #1;
    end


    sw_signal = 1;
    repeat (40) @(negedge clk);  

    repeat (20) begin
    sw_signal = 0;
    #1;
    sw_signal = 1;
    #1;
    end



    sw_signal = 0;
    repeat (40) @(negedge clk);  

$display ("End of simulation"); 
$stop;
end




endmodule

Design_phase/5_Debouncing_Circuit/Debouncing_Circuit.vcd
$date
	Mon Aug 31 17:03:59 2026
$end
$version
	QuestaSim Version 2021.1
$end
$timescale
	1ns
$end

$scope module tb_Debouncing_Circuit $end
$var reg 1 ! rst_n $end
$var reg 1 " clk $end
$var reg 1 # sw_signal $end
$var wire 1 $ db $end

$scope module Debouncing_Circuit_UUT $end
$var parameter 4 % ZERO $end
$var parameter 4 & WAIT1_1 $end
$var parameter 4 ' WAIT1_2 $end
$var parameter 4 ( WAIT1_3 $end
$var parameter 4 ) ONE $end
$var parameter 4 * WAIT0_1 $end
$var parameter 4 + WAIT0_2 $end
$var parameter 4 , WAIT0_3 $end
$var wire 1 - sw_signal $end
$var wire 1 . clk $end
$var wire 1 / rst_n $end
$var reg 1 0 db $end
$var reg 4 1 current_state [3:0] $end
$var reg 4 2 next_state [3:0] $end
$var wire 1 3 m_tick $end

$scope module counter $end
$var parameter 32 4 CLK_FREQ $end
$var parameter 32 5 CLK_DIVIDER $end
$var parameter 32 6 COUNTER_MAX $end
$var wire 1 . clk $end
$var wire 1 / rst_n $end
$var reg 1 7 m_tick $end
$var reg 4 8 counter [3:0] $end
$upscope $end
$upscope $end
$upscope $end
$enddefinitions $end
#0
$dumpvars
0!
0"
0#
00
b0 1
b0 2
07
b0 8
b0 %
b1 &
b11 '
b10 (
b1000 )
b1001 *
b1011 +
b1010 ,
b101111101011110000100000000 4
b100110001001011010000000 5
b1010 6
0$
03
0/
0.
0-
$end
#5
1"
1.
#10
0"
0.
1!
1/
#11
1#
1-
b1 2
#12
0#
0-
b0 2
#13
1#
1-
b1 2
#14
0#
0-
b0 2
#15
1"
1#
1.
1-
b1 2
b1 8
b1 1
#16
0#
0-
b0 2
#17
1#
1-
b1 2
#18
0#
0-
b0 2
#19
1#
1-
b1 2
#20
0"
0#
0.
0-
b0 2
#21
1#
1-
b1 2
#22
0#
0-
b0 2
#23
1#
1-
b1 2
#24
0#
0-
b0 2
#25
1"
1#
1.
1-
b1 2
b10 8
#26
0#
0-
b0 2
#27
1#
1-
b1 2
#28
0#
0-
b0 2
#29
1#
1-
b1 2
#30
0"
0#
0.
0-
b0 2
#31
1#
1-
b1 2
#32
0#
0-
b0 2
#33
1#
1-
b1 2
#34
0#
0-
b0 2
#35
1"
1#
1.
1-
b1 2
b11 8
#36
0#
0-
b0 2
#37
1#
1-
b1 2
#38
0#
0-
b0 2
#39
1#
1-
b1 2
#40
0"
0#
0.
0-
b0 2
#41
1#
1-
b1 2
#42
0#
0-
b0 2
#43
1#
1-
b1 2
#44
0#
0-
b0 2
#45
1"
1#
1.
1-
b1 2
b100 8
#46
0#
0-
b0 2
#47
1#
1-
b1 2
#48
0#
0-
b0 2
#49
1#
1-
b1 2
#50
0"
0#
0.
0-
b0 2
#51
1#
1-
b1 2
#55
1"
1.
b101 8
#60
0"
0.
#65
1"
1.
b110 8
#70
0"
0.
#75
1"
1.
b111 8
#80
0"
0.
#85
1"
1.
b1000 8
#90
0"
0.
#95
1"
1.
b1001 8
#100
0"
0.
#105
1"
1.
b1010 8
#110
0"
0.
#115
1"
1.
b0 8
17
13
b11 2
#120
0"
0.
#125
1"
1.
b1 8
07
b11 1
03
#130
0"
0.
#135
1"
1.
b10 8
#140
0"
0.
#145
1"
1.
b11 8
#150
0"
0.
#155
1"
1.
b100 8
#160
0"
0.
#165
1"
1.
b101 8
#170
0"
0.
#175
1"
1.
b110 8
#180
0"
0.
#185
1"
1.
b111 8
#190
0"
0.
#195
1"
1.
b1000 8
#200
0"
0.
#205
1"
1.
b1001 8
#210
0"
0.
#215
1"
1.
b1010 8
#220
0"
0.
#225
1"
1.
b0 8
17
13
b10 2
#230
0"
0.
#235
1"
1.
b1 8
07
b10 1
03
#240
0"
0.
#245
1"
1.
b10 8
#250
0"
0.
#255
1"
1.
b11 8
#260
0"
0.
#265
1"
1.
b100 8
#270
0"
0.
#275
1"
1.
b101 8
#280
0"
0.
#285
1"
1.
b110 8
#290
0"
0.
#295
1"
1.
b111 8
#300
0"
0.
#305
1"
1.
b1000 8
#310
0"
0.
#315
1"
1.
b1001 8
#320
0"
0.
#325
1"
1.
b1010 8
#330
0"
0.
#335
1"
1.
b0 8
17
13
b1000 2
#340
0"
0.
#345
1"
1.
b1 8
07
b1000 1
03
10
1$
#350
0"
0.
#355
1"
1.
b10 8
#360
0"
0.
#365
1"
1.
b11 8
#370
0"
0.
#375
1"
1.
b100 8
#380
0"
0.
#385
1"
1.
b101 8
#390
0"
0.
#395
1"
1.
b110 8
#400
0"
0.
#405
1"
1.
b111 8
#410
0"
0.
#415
1"
1.
b1000 8
#420
0"
0.
#425
1"
1.
b1001 8
#430
0"
0.
#435
1"
1.
b1010 8
#440
0"
0.
#445
1"
1.
b0 8
17
13
#450
0"
0.
0#
0-
b1001 2
#451
1#
1-
b1000 2
#452
0#
0-
b1001 2
#453
1#
1-
b1000 2
#454
0#
0-
b1001 2
#455
1"
1#
1.
1-
b1000 2
b1 8
07
03
#456
0#
0-
b1001 2
#457
1#
1-
b1000 2
#458
0#
0-
b1001 2
#459
1#
1-
b1000 2
#460
0"
0#
0.
0-
b1001 2
#461
1#
1-
b1000 2
#462
0#
0-
b1001 2
#463
1#
1-
b1000 2
#464
0#
0-
b1001 2
#465
1"
1#
1.
1-
b1000 2
b10 8
#466
0#
0-
b1001 2
#467
1#
1-
b1000 2
#468
0#
0-
b1001 2
#469
1#
1-
b1000 2
#470
0"
0#
0.
0-
b1001 2
#471
1#
1-
b1000 2
#472
0#
0-
b1001 2
#473
1#
1-
b1000 2
#474
0#
0-
b1001 2
#475
1"
1#
1.
1-
b1000 2
b11 8
#476
0#
0-
b1001 2
#477
1#
1-
b1000 2
#478
0#
0-
b1001 2
#479
1#
1-
b1000 2
#480
0"
0#
0.
0-
b1001 2
#481
1#
1-
b1000 2
#482
0#
0-
b1001 2
#483
1#
1-
b1000 2
#484
0#
0-
b1001 2
#485
1"
1#
1.
1-
b1000 2
b100 8
#486
0#
0-
b1001 2
#487
1#
1-
b1000 2
#488
0#
0-
b1001 2
#489
1#
1-
b1000 2
#490
0"
0#
0.
0-
b1001 2
#495
1"
1.
b101 8
b1001 1
#500
0"
0.
#505
1"
1.
b110 8
#510
0"
0.
#515
1"
1.
b111 8
#520
0"
0.
#525
1"
1.
b1000 8
#530
0"
0.
#535
1"
1.
b1001 8
#540
0"
0.
#545
1"
1.
b1010 8
#550
0"
0.
#555
1"
1.
b0 8
17
13
b1011 2
#560
0"
0.
#565
1"
1.
b1 8
07
b1011 1
03
#570
0"
0.
#575
1"
1.
b10 8
#580
0"
0.
#585
1"
1.
b11 8
#590
0"
0.
#595
1"
1.
b100 8
#600
0"
0.
#605
1"
1.
b101 8
#610
0"
0.
#615
1"
1.
b110 8
#620
0"
0.
#625
1"
1.
b111 8
#630
0"
0.
#635
1"
1.
b1000 8
#640
0"
0.
#645
1"
1.
b1001 8
#650
0"
0.
#655
1"
1.
b1010 8
#660
0"
0.
#665
1"
1.
b0 8
17
13
b1010 2
#670
0"
0.
#675
1"
1.
b1 8
07
b1010 1
03
#680
0"
0.
#685
1"
1.
b10 8
#690
0"
0.
#695
1"
1.
b11 8
#700
0"
0.
#705
1"
1.
b100 8
#710
0"
0.
#715
1"
1.
b101 8
#720
0"
0.
#725
1"
1.
b110 8
#730
0"
0.
#735
1"
1.
b111 8
#740
0"
0.
#745
1"
1.
b1000 8
#750
0"
0.
#755
1"
1.
b1001 8
#760
0"
0.
#765
1"
1.
b1010 8
#770
0"
0.
#775
1"
1.
b0 8
17
13
b0 2
#780
0"
0.
#785
1"
1.
b1 8
07
b0 1
03
00
0$
#790
0"
0.
#795
1"
1.
b10 8
#800
0"
0.
#805
1"
1.
b11 8
#810
0"
0.
#815
1"
1.
b100 8
#820
0"
0.
#825
1"
1.
b101 8
#830
0"
0.
#835
1"
1.
b110 8
#840
0"
0.
#845
1"
1.
b111 8
#850
0"
0.
#855
1"
1.
b1000 8
#860
0"
0.
#865
1"
1.
b1001 8
#870
0"
0.
#875
1"
1.
b1010 8
#880
0"
0.
#885
1"
1.
b0 8
17
13
